nimbusPython/NimbusClient.py
nimbusPython/__init__.py
nimbus_python-0.0.6.dist-info/LICENSE
nimbus_python-0.0.6.dist-info/METADATA
nimbus_python-0.0.6.dist-info/WHEEL
nimbus_python-0.0.6.dist-info/top_level.txt
nimbus_python-0.0.6.dist-info/RECORD
